[
  {
    "remapped_index": 0,
    "raw_label": 1,
    "dice": 0.7868126034736633
  },
  {
    "remapped_index": 1,
    "raw_label": 2,
    "dice": 0.7791271209716797
  },
  {
    "remapped_index": 2,
    "raw_label": 3,
    "dice": 0.7984947562217712
  },
  {
    "remapped_index": 3,
    "raw_label": 4,
    "dice": 0.7578657269477844
  },
  {
    "remapped_index": 4,
    "raw_label": 5,
    "dice": 0.7474988102912903
  },
  {
    "remapped_index": 5,
    "raw_label": 6,
    "dice": 0.7388584017753601
  },
  {
    "remapped_index": 6,
    "raw_label": 7,
    "dice": 0.7195605635643005
  },
  {
    "remapped_index": 7,
    "raw_label": 8,
    "dice": 0.7207663059234619
  },
  {
    "remapped_index": 8,
    "raw_label": 9,
    "dice": 0.7168537974357605
  },
  {
    "remapped_index": 9,
    "raw_label": 10,
    "dice": 0.7304630279541016
  },
  {
    "remapped_index": 10,
    "raw_label": 11,
    "dice": 0.7252216935157776
  },
  {
    "remapped_index": 11,
    "raw_label": 12,
    "dice": 0.7036231160163879
  },
  {
    "remapped_index": 12,
    "raw_label": 13,
    "dice": 0.6891201734542847
  },
  {
    "remapped_index": 13,
    "raw_label": 14,
    "dice": 0.6357110142707825
  },
  {
    "remapped_index": 14,
    "raw_label": 15,
    "dice": 0.0
  },
  {
    "remapped_index": 15,
    "raw_label": 16,
    "dice": 0.8822585940361023
  },
  {
    "remapped_index": 16,
    "raw_label": 17,
    "dice": 0.8743188977241516
  },
  {
    "remapped_index": 17,
    "raw_label": 18,
    "dice": 0.8841687440872192
  },
  {
    "remapped_index": 18,
    "raw_label": 19,
    "dice": 0.7556421160697937
  },
  {
    "remapped_index": 19,
    "raw_label": 20,
    "dice": 0.7908016443252563
  },
  {
    "remapped_index": 20,
    "raw_label": 21,
    "dice": 0.8007280230522156
  },
  {
    "remapped_index": 21,
    "raw_label": 22,
    "dice": 0.7867712378501892
  },
  {
    "remapped_index": 22,
    "raw_label": 23,
    "dice": 0.7016600966453552
  },
  {
    "remapped_index": 23,
    "raw_label": 24,
    "dice": 0.685137927532196
  },
  {
    "remapped_index": 24,
    "raw_label": 25,
    "dice": 0.6624109148979187
  },
  {
    "remapped_index": 25,
    "raw_label": 26,
    "dice": 0.6661335825920105
  },
  {
    "remapped_index": 26,
    "raw_label": 27,
    "dice": 0.7426294684410095
  },
  {
    "remapped_index": 27,
    "raw_label": 28,
    "dice": 0.7427695393562317
  },
  {
    "remapped_index": 28,
    "raw_label": 29,
    "dice": 0.662604808807373
  },
  {
    "remapped_index": 29,
    "raw_label": 30,
    "dice": 0.638989269733429
  },
  {
    "remapped_index": 30,
    "raw_label": 31,
    "dice": 0.7516878843307495
  },
  {
    "remapped_index": 31,
    "raw_label": 32,
    "dice": 0.7370879650115967
  },
  {
    "remapped_index": 32,
    "raw_label": 33,
    "dice": 0.7418171167373657
  },
  {
    "remapped_index": 33,
    "raw_label": 34,
    "dice": 0.7553917765617371
  },
  {
    "remapped_index": 34,
    "raw_label": 35,
    "dice": 0.7464088797569275
  },
  {
    "remapped_index": 35,
    "raw_label": 36,
    "dice": 0.5945159196853638
  },
  {
    "remapped_index": 36,
    "raw_label": 37,
    "dice": 0.780738115310669
  },
  {
    "remapped_index": 37,
    "raw_label": 38,
    "dice": 0.7834662795066833
  },
  {
    "remapped_index": 38,
    "raw_label": 39,
    "dice": 0.819035530090332
  },
  {
    "remapped_index": 39,
    "raw_label": 40,
    "dice": 0.8285101056098938
  },
  {
    "remapped_index": 40,
    "raw_label": 41,
    "dice": 0.8472371101379395
  },
  {
    "remapped_index": 41,
    "raw_label": 42,
    "dice": 0.8436741232872009
  },
  {
    "remapped_index": 42,
    "raw_label": 43,
    "dice": 0.726496160030365
  },
  {
    "remapped_index": 43,
    "raw_label": 44,
    "dice": 0.7046087980270386
  },
  {
    "remapped_index": 44,
    "raw_label": 45,
    "dice": 0.8585319519042969
  },
  {
    "remapped_index": 45,
    "raw_label": 46,
    "dice": 0.857731282711029
  },
  {
    "remapped_index": 46,
    "raw_label": 47,
    "dice": 0.7422663569450378
  },
  {
    "remapped_index": 47,
    "raw_label": 48,
    "dice": 0.8729864358901978
  },
  {
    "remapped_index": 48,
    "raw_label": 49,
    "dice": 0.8634740710258484
  },
  {
    "remapped_index": 49,
    "raw_label": 50,
    "dice": 0.0
  },
  {
    "remapped_index": 50,
    "raw_label": 51,
    "dice": 0.0
  },
  {
    "remapped_index": 51,
    "raw_label": 52,
    "dice": 0.7335501909255981
  },
  {
    "remapped_index": 52,
    "raw_label": 53,
    "dice": 0.0
  },
  {
    "remapped_index": 53,
    "raw_label": 54,
    "dice": 0.0
  },
  {
    "remapped_index": 54,
    "raw_label": 55,
    "dice": 0.7311882376670837
  },
  {
    "remapped_index": 55,
    "raw_label": 56,
    "dice": 0.8150098919868469
  },
  {
    "remapped_index": 56,
    "raw_label": 57,
    "dice": 0.8121361136436462
  },
  {
    "remapped_index": 57,
    "raw_label": 58,
    "dice": 0.8177253007888794
  },
  {
    "remapped_index": 58,
    "raw_label": 59,
    "dice": 0.8229507803916931
  },
  {
    "remapped_index": 59,
    "raw_label": 60,
    "dice": 0.7326034903526306
  },
  {
    "remapped_index": 60,
    "raw_label": 61,
    "dice": 0.7559905052185059
  },
  {
    "remapped_index": 61,
    "raw_label": 62,
    "dice": 0.8429726958274841
  },
  {
    "remapped_index": 62,
    "raw_label": 63,
    "dice": 0.8555971384048462
  },
  {
    "remapped_index": 63,
    "raw_label": 64,
    "dice": 0.8700351715087891
  },
  {
    "remapped_index": 64,
    "raw_label": 65,
    "dice": 0.858981728553772
  },
  {
    "remapped_index": 65,
    "raw_label": 66,
    "dice": 0.7255751490592957
  },
  {
    "remapped_index": 66,
    "raw_label": 67,
    "dice": 0.7225767970085144
  },
  {
    "remapped_index": 67,
    "raw_label": 68,
    "dice": 0.7360754013061523
  },
  {
    "remapped_index": 68,
    "raw_label": 69,
    "dice": 0.7648898959159851
  },
  {
    "remapped_index": 69,
    "raw_label": 70,
    "dice": 0.8176597952842712
  },
  {
    "remapped_index": 70,
    "raw_label": 71,
    "dice": 0.8167193531990051
  },
  {
    "remapped_index": 71,
    "raw_label": 72,
    "dice": 0.7632779479026794
  },
  {
    "remapped_index": 72,
    "raw_label": 73,
    "dice": 0.738872230052948
  },
  {
    "remapped_index": 73,
    "raw_label": 74,
    "dice": 0.7871765494346619
  },
  {
    "remapped_index": 74,
    "raw_label": 75,
    "dice": 0.7983903288841248
  },
  {
    "remapped_index": 75,
    "raw_label": 76,
    "dice": 0.8026780486106873
  },
  {
    "remapped_index": 76,
    "raw_label": 77,
    "dice": 0.8074527978897095
  },
  {
    "remapped_index": 77,
    "raw_label": 78,
    "dice": 0.3320635259151459
  },
  {
    "remapped_index": 78,
    "raw_label": 79,
    "dice": 0.42864057421684265
  },
  {
    "remapped_index": 79,
    "raw_label": 80,
    "dice": 0.8643987774848938
  },
  {
    "remapped_index": 80,
    "raw_label": 81,
    "dice": 0.8705219626426697
  },
  {
    "remapped_index": 81,
    "raw_label": 82,
    "dice": 0.5127810835838318
  },
  {
    "remapped_index": 82,
    "raw_label": 83,
    "dice": 0.3286841809749603
  },
  {
    "remapped_index": 83,
    "raw_label": 84,
    "dice": 0.7255870699882507
  },
  {
    "remapped_index": 84,
    "raw_label": 85,
    "dice": 0.7421261668205261
  },
  {
    "remapped_index": 85,
    "raw_label": 86,
    "dice": 0.7426789999008179
  }
]